LICENSE
README.md
post_fetch_hook/__init__.py
post_fetch_hook/mixins.py
post_fetch_hook/models.py
post_fetch_hook/py.typed
post_fetch_hook/typing.py
django_post_fetch_hook-0.0.3.dist-info/LICENSE
django_post_fetch_hook-0.0.3.dist-info/METADATA
django_post_fetch_hook-0.0.3.dist-info/WHEEL
django_post_fetch_hook-0.0.3.dist-info/RECORD
