Metadata-Version: 2.1
Name: django-post-fetch-hook
Version: 0.0.3
Summary: Modify data fetched from a database after it has been fetched but before it has been cached in django's result cache.
Home-page: https://mrthearman.github.io/django-post-fetch-hook
License: MIT
Keywords: django,post,fetch,hook,database
Author: Matti Lamppu
Author-email: lamppu.matti.akseli@gmail.com
Requires-Python: >=3.9,<4
Classifier: Environment :: Web Environment
Classifier: Intended Audience :: Developers
Classifier: License :: OSI Approved :: MIT License
Classifier: Natural Language :: English
Classifier: Operating System :: OS Independent
Classifier: Programming Language :: Python
Classifier: Programming Language :: Python :: 3
Classifier: Programming Language :: Python :: 3.9
Classifier: Programming Language :: Python :: 3.10
Classifier: Programming Language :: Python :: 3.11
Classifier: Programming Language :: Python :: 3.12
Classifier: Programming Language :: Python :: 3 :: Only
Requires-Dist: Django (>=3.2)
Project-URL: Bug Tracker, https://github.com/MrThearMan/django-post-fetch-hook/issues
Project-URL: Repository, https://github.com/MrThearMan/django-post-fetch-hook
